protopy/doc_generator.py
protopy/engine.py
protopy_lib-0.2.0.dist-info/WHEEL
protopy_lib-0.2.0.dist-info/METADATA
protopy_lib-0.2.0.dist-info/RECORD
