Metadata-Version: 2.1
Name: protopy-lib
Version: 0.2.0
Summary: 
Author: bennylut
Requires-Python: >=3.6,<4.0
Classifier: Programming Language :: Python :: 3
Classifier: Programming Language :: Python :: 3.6
Classifier: Programming Language :: Python :: 3.7
Classifier: Programming Language :: Python :: 3.8
Classifier: Programming Language :: Python :: 3.9
Classifier: Programming Language :: Python :: 3.10
Requires-Dist: Jinja2 (>=3.0.1,<4.0.0)
Requires-Dist: cleo (>=1.0.0a4,<2.0.0)
